bug.py
PyBug-1.2.1.dist-info/METADATA
PyBug-1.2.1.dist-info/RECORD
PyBug-1.2.1.dist-info/WHEEL
PyBug-1.2.1.dist-info/top_level.txt
