Metadata-Version: 2.1
Name: PyBug
Version: 1.2.1
Summary: PyBug extends Python's interactive debugger (pdb), making it simpler to add breakpoints to your code.
Home-page: http://github.com/millerdev/PyBug
Author: Daniel Miller
Author-email: millerdev@gmail.com
License: UNKNOWN
Keywords: debug pdb extension
Platform: UNKNOWN
